list_screen/__init__.py
list_screen/console_element.py
list_screen/dynamic_element.py
list_screen/main.py
list_screen-0.22.dist-info/LICENSE.txt
list_screen-0.22.dist-info/METADATA
list_screen-0.22.dist-info/WHEEL
list_screen-0.22.dist-info/top_level.txt
list_screen-0.22.dist-info/RECORD
