Metadata-Version: 2.1
Name: list-screen
Version: 0.22
Summary: A package to manage input and output
Home-page: https://github.com/JeremyMoeglich/Python-Cmd-Screen
Author: Jeremy Moeglich
Author-email: jeremy.moeglich@gmail.com
License: UNKNOWN
Project-URL: Bug Tracker, https://github.com/JeremyMoeglich/Python-Cmd-Screen/issues
Platform: UNKNOWN
Classifier: Programming Language :: Python :: 3
Classifier: License :: OSI Approved :: MIT License
Classifier: Operating System :: OS Independent
Requires-Python: >=3.9
License-File: LICENSE.txt
Requires-Dist: aioconsole (>=0.4.1)
Requires-Dist: colorama (>=0.4.4)
